cytoflow/__init__.py
cytoflow/_version.py
cytoflow/experiment.py
cytoflow/operations/__init__.py
cytoflow/operations/autofluorescence.py
cytoflow/operations/base_op_views.py
cytoflow/operations/bead_calibration.py
cytoflow/operations/binning.py
cytoflow/operations/bleedthrough_linear.py
cytoflow/operations/channel_stat.py
cytoflow/operations/color_translation.py
cytoflow/operations/density.py
cytoflow/operations/flowpeaks.py
cytoflow/operations/frame_stat.py
cytoflow/operations/gaussian.py
cytoflow/operations/i_operation.py
cytoflow/operations/import_op.py
cytoflow/operations/kmeans.py
cytoflow/operations/pca.py
cytoflow/operations/polygon.py
cytoflow/operations/quad.py
cytoflow/operations/range.py
cytoflow/operations/range2d.py
cytoflow/operations/ratio.py
cytoflow/operations/threshold.py
cytoflow/operations/xform_stat.py
cytoflow/scripts/__init__.py
cytoflow/scripts/channel_voltages.py
cytoflow/scripts/fcs_metadata.py
cytoflow/scripts/parse_beads.py
cytoflow/tests/__init__.py
cytoflow/tests/nose_setup.py
cytoflow/tests/test_autofluorescence.py
cytoflow/tests/test_barchart.py
cytoflow/tests/test_base.py
cytoflow/tests/test_basic_views.py
cytoflow/tests/test_bead_calibration.py
cytoflow/tests/test_binning.py
cytoflow/tests/test_bleedthrough_linear.py
cytoflow/tests/test_channel_stat.py
cytoflow/tests/test_color_translation.py
cytoflow/tests/test_density_op.py
cytoflow/tests/test_densityplot.py
cytoflow/tests/test_experiment.py
cytoflow/tests/test_export.py
cytoflow/tests/test_flowpeaks.py
cytoflow/tests/test_frame_stat.py
cytoflow/tests/test_gaussian.py
cytoflow/tests/test_gaussian_1d.py
cytoflow/tests/test_gaussian_2d.py
cytoflow/tests/test_histogram.py
cytoflow/tests/test_histogram_2d.py
cytoflow/tests/test_hlog.py
cytoflow/tests/test_import.py
cytoflow/tests/test_kde1d.py
cytoflow/tests/test_kde2d.py
cytoflow/tests/test_kmeans.py
cytoflow/tests/test_log.py
cytoflow/tests/test_logicle.py
cytoflow/tests/test_parallel_coords.py
cytoflow/tests/test_pca.py
cytoflow-1.2.dist-info/LICENSE.txt
cytoflow-1.2.dist-info/METADATA
cytoflow-1.2.dist-info/WHEEL
cytoflow-1.2.dist-info/entry_points.txt
cytoflow-1.2.dist-info/top_level.txt
cytoflow-1.2.dist-info/RECORD
