Metadata-Version: 2.1
Name: cytoflow
Version: 1.2
Summary: Python tools for quantitative, reproducible flow cytometry analysis
Home-page: https://github.com/cytoflow/cytoflow
Author: Brian Teague
Author-email: bpteague@gmail.edu
License: GPLv2
Keywords: flow cytometry scipy
Platform: UNKNOWN
Classifier: Development Status :: 5 - Production/Stable
Classifier: Environment :: Console
Classifier: Environment :: MacOS X
Classifier: Environment :: Win32 (MS Windows)
Classifier: Environment :: X11 Applications :: Qt
Classifier: Intended Audience :: Science/Research
Classifier: License :: OSI Approved :: GNU General Public License v2 (GPLv2)
Classifier: Natural Language :: English
Classifier: Operating System :: MacOS
Classifier: Operating System :: Microsoft :: Windows
Classifier: Operating System :: POSIX :: Linux
Classifier: Programming Language :: Python :: 3.4
Classifier: Programming Language :: Python :: 3.5
Classifier: Programming Language :: Python :: 3.6
Classifier: Programming Language :: Python :: 3.7
Classifier: Programming Language :: Python :: Implementation :: CPython
Classifier: Topic :: Scientific/Engineering :: Bio-Informatics
Classifier: Topic :: Software Development :: Libraries :: Python Modules
License-File: LICENSE.txt
Requires-Dist: numpy (==1.21.2)
Requires-Dist: pandas (==1.3.5)
Requires-Dist: matplotlib (==3.5.0)
Requires-Dist: bottleneck (==1.3.2)
Requires-Dist: numexpr (==2.8.1)
Requires-Dist: scipy (==1.7.3)
Requires-Dist: scikit-learn (==1.0.1)
Requires-Dist: seaborn (==0.11.2)
Requires-Dist: statsmodels (==0.13.0)
Requires-Dist: natsort (==7.1.1)
Requires-Dist: numba (==0.53.1)
Requires-Dist: traits (==6.2.0)
Requires-Dist: traitsui (==7.2.1)
Requires-Dist: pyface (==7.3.0)
Requires-Dist: envisage (==6.0.1)
Requires-Dist: nbformat (==5.1.3)
Requires-Dist: python-dateutil (==2.8.2)
Requires-Dist: importlib-resources (==5.2.0)
Requires-Dist: pyopengl (==3.1.1a1)
Requires-Dist: camel (==0.1.2)
Requires-Dist: yapf (==0.30.0)
